[
  {
    "id": 1,
    "first_name": "أحمد",
    "last_name": "الخولي",
    "time_ago": "منذ ساعتين",
    "tags": ["إنتاج نباتي", "ري"],
    "content": "هل تعلم أن الري بالتنقيط يقلل من استهلاك المياه بنسبة تصل إلى 50% مقارنة بالري بالغمر؟ كما يساهم في الحد من نمو الحشائش. يجب التأكد من صيانة نقاط التنقيط بشكل دوري لتجنب الانسداد.",
    "type": "معلومة",
    "comments_count": 5,
    "likes_count": 25,
    "shares_count": 3,
    "image_paths": [
      "assets/images/post1_img1.jpg",
      "assets/images/post1_img2.jpg",
      "assets/images/post1_img3.jpg"
    ]
  },
  {
    "id": 2,
    "first_name": "فاطمة",
    "last_name": "جابر",
    "time_ago": "منذ 4 أيام",
    "tags": ["أمراض نبات", "وقاية"],
    "content": "سؤال: لاحظت ظهور بقع بنية صغيرة على أوراق نبات الطماطم، ما هي احتمالات هذا المرض وكيف يمكنني علاجه بأقل مبيدات ممكنة؟ الأوراق تبدأ بالاصفرار ثم تسقط. أرجو المساعدة من ذوي الخبرة.",
    "type": "سؤال",
    "comments_count": 8,
    "likes_count": 14,
    "shares_count": 1
  },
  {
    "id": 3,
    "first_name": "محمد",
    "last_name": "سالم",
    "time_ago": "منذ شهر",
    "tags": ["حشرات", "مبيدات"],
    "content": "المنّ (Aphids) من الحشرات المزعجة التي تسبب أضراراً كبيرة للمحاصيل. للتخلص منها بشكل فعال، يمكن استخدام زيت النيم أو الصابون الزراعي كحل عضوي قبل اللجوء للمبيدات الكيميائية. ",
    "type": "معلومة",
    "comments_count": 3,
    "likes_count": 35,
    "shares_count": 5,
    "image_paths": [
      "assets/images/post3_img1.jpg",
      "assets/images/post3_img2.jpg"
    ]
  },
  {
    "id": 4,
    "first_name": "ليلى",
    "last_name": "حسن",
    "time_ago": "منذ 5 دقائق",
    "tags": ["إنتاج نباتي", "تسميد"],
    "content": "ما هو أفضل وقت لإضافة سماد NPK (19-19-19) لأشجار الحمضيات؟ وهل هناك جرعة محددة تُنصح بها للفدان الواحد في مرحلة النمو الخضري؟",
    "type": "سؤال",
    "comments_count": 10,
    "likes_count": 18,
    "shares_count": 2
  },
  {
    "id": 5,
    "first_name": "علي",
    "last_name": "فؤاد",
    "time_ago": "منذ أسبوعين",
    "tags": ["أمراض نبات", "فطريات"],
    "content": "البياض الدقيقي مرض فطري ينتشر بسرعة في الظروف الرطبة والمعتدلة. للوقاية، يجب تحسين التهوية وتقليل كثافة النباتات. العلاج يكون باستخدام مبيدات فطرية جهازية.",
    "type": "معلومة",
    "comments_count": 6,
    "likes_count": 42,
    "shares_count": 7,
    "image_paths": [
      "assets/images/post5_img1.jpg",
      "assets/images/post5_img2.jpg",
      "assets/images/post5_img3.jpg",
      "assets/images/post5_img4.jpg"
    ]
  },
  {
    "id": 6,
    "first_name": "سارة",
    "last_name": "منصور",
    "time_ago": "منذ 3 أسابيع",
    "tags": ["مبيدات", "سلامة"],
    "content": "نصيحة هامة: عند استخدام أي مبيد كيميائي، يجب قراءة ملصق التعليمات بالكامل والالتزام بارتداء معدات الوقاية الشخصية (الكمامة، القفازات، النظارات). السلامة أولاً!",
    "type": "معلومة",
    "comments_count": 4,
    "likes_count": 22,
    "shares_count": 6
  },
  {
    "id": 7,
    "first_name": "خالد",
    "last_name": "مراد",
    "time_ago": "منذ سنة",
    "tags": ["حشرات", "مكافحة حيوية"],
    "content": "ما هي الكائنات الحية الدقيقة أو المفترسات التي يمكن استخدامها للمكافحة الحيوية ضد الحشرات القشرية في البيوت المحمية؟ هل جرب أحدكم استخدام الطفيليات؟",
    "type": "سؤال",
    "comments_count": 7,
    "likes_count": 10,
    "shares_count": 0
  },
  {
    "id": 8,
    "first_name": "نادية",
    "last_name": "يوسف",
    "time_ago": "منذ 15 دقيقة",
    "tags": ["إنتاج نباتي", "تربة"],
    "content": "معلومة سريعة عن خصوبة التربة: إضافة المواد العضوية (كالسماد البلدي المتحلل) يحسن من قوام التربة وقدرتها على الاحتفاظ بالماء والمغذيات الأساسية للنبات.",
    "type": "معلومة",
    "comments_count": 3,
    "likes_count": 17,
    "shares_count": 2
  },
  {
    "id": 9,
    "first_name": "أيمن",
    "last_name": "عادل",
    "time_ago": "منذ 9 شهور",
    "tags": ["أمراض نبات", "محاصيل حقلية"],
    "content": "لدي مشكلة في محصول القمح، تظهر فيه خطوط صفراء طولية على الأوراق. ما هو التشخيص المحتمل؟ هل هي أعراض نقص عنصر معين أم مرض فيروسي؟ وكيف يمكنني التأكد؟",
    "type": "سؤال",
    "comments_count": 9,
    "likes_count": 29,
    "shares_count": 4,
    "image_paths": [
      "assets/images/post9_img1.jpg",
      "assets/images/post9_img2.jpg",
      "assets/images/post9_img3.jpg",
      "assets/images/post9_img4.jpg",
      "assets/images/post9_img5.jpg"
    ]
  },
  {
    "id": 10,
    "first_name": "ريم",
    "last_name": "سعد",
    "time_ago": "منذ 6 ساعات",
    "tags": ["مبيدات", "أعشاب ضارة"],
    "content": "نشرة مختصرة عن مكافحة الأعشاب الضارة في بداية الموسم: يجب اختيار المبيد المناسب لنوع العشبة والمحصول المزروع لتجنب أي ضرر للنباتات الأساسية. الاستشارة الزراعية مهمة قبل الرش.",
    "type": "معلومة",
    "comments_count": 6,
    "likes_count": 12,
    "shares_count": 1
  }
]